setup.py
confirmaction/__init__.py
confirmaction/admin.py
confirmaction/decorators.py
confirmaction/exceptions.py
confirmaction/main.py
confirmaction/models.py
confirmaction/settings.py
confirmaction/utils.py
confirmaction/migrations/0001_initial.py
confirmaction/migrations/0002_auto__add_field_action_executed__add_field_action_action_status__add_f.py
confirmaction/migrations/0003_auto__add_field_action_user_contact.py
confirmaction/migrations/0004_rename_confirm_code_to_code_hash.py
confirmaction/migrations/0005_auto__add_field_action_scope.py
confirmaction/migrations/__init__.py
django_confirmaction.egg-info/PKG-INFO
django_confirmaction.egg-info/SOURCES.txt
django_confirmaction.egg-info/dependency_links.txt
django_confirmaction.egg-info/requires.txt
django_confirmaction.egg-info/top_level.txt