Metadata-Version: 1.1
Name: django-confirmaction
Version: 0.0.3
Summary: Django battery for confirm some action via email, sms, etc
Home-page: https://github.com/Zapix/django-confirmaction
Author: Aleksandr Aibulatov
Author-email: zap.aibulatov@gmail.com
License: BSD
Keywords: django,battery,confirm action
Platform: UNKNOWN
Classifier: Development Status :: 2 - Pre-Alpha
Classifier: Framework :: Django
Classifier: Programming Language :: Python :: 2.7
Classifier: Topic :: Utilities
Classifier: License :: OSI Approved :: BSD License
